infoalign/__init__.py
infoalign/cli.py
infoalign/representer.py
infoalign/utils.py
infoalign/models/conv.py
infoalign/models/gnn.py
infoalign-0.1.1.dist-info/LICENSE
infoalign-0.1.1.dist-info/METADATA
infoalign-0.1.1.dist-info/WHEEL
infoalign-0.1.1.dist-info/entry_points.txt
infoalign-0.1.1.dist-info/top_level.txt
infoalign-0.1.1.dist-info/RECORD
