Metadata-Version: 2.1
Name: infoalign
Version: 0.1.1
Summary: A package for the paper: learning molecular representation in a cell
Author-email: Gang Liu <gliu7@nd.edu>
License: MIT
Project-URL: Homepage, https://github.com/liugangcode/InfoAlign
Project-URL: Bug Tracker, https://github.com/liugangcode/InfoAlign/issues
Classifier: Programming Language :: Python :: 3
Classifier: License :: OSI Approved :: MIT License
Classifier: Operating System :: OS Independent
Requires-Python: >=3.8
License-File: LICENSE
Requires-Dist: torch>=2.2.0
Requires-Dist: torch-geometric>=2.6.1
Requires-Dist: numpy
Requires-Dist: pandas>=2.2.3
Requires-Dist: click
Requires-Dist: huggingface-hub>=0.22.2
Requires-Dist: joblib>=1.3.2
Requires-Dist: networkx>=3.2.1
Requires-Dist: ogb>=1.3.6
Requires-Dist: PyYAML>=6.0.2
Requires-Dist: rdkit>=2023.9.5
Requires-Dist: scikit-learn>=1.4.1.post1
Requires-Dist: scipy>=1.14.1
Requires-Dist: tqdm>=4.66.2
Provides-Extra: dev
Requires-Dist: pytest>=7.0; extra == "dev"
Requires-Dist: black; extra == "dev"
Requires-Dist: isort; extra == "dev"
Requires-Dist: flake8; extra == "dev"
